DBService/__init__.py
DBService/dbcore.py
DBService/dbcore_old.py
dbservice-2.1.3.dist-info/METADATA
dbservice-2.1.3.dist-info/WHEEL
dbservice-2.1.3.dist-info/licenses/LICENSE
dbservice-2.1.3.dist-info/RECORD
