Metadata-Version: 2.1
Name: DBService
Version: 2.1.3
Summary: a Database Wrapper for Redis and MySQL
Project-URL: Homepage, https://pypi.org/project/DBService/
Author-email: "hang.zhang" <hhczy1003@163.com>, "Marrin.Hu" <himarrin@gmail.com>
License-File: LICENSE
Classifier: License :: OSI Approved :: MIT License
Classifier: Programming Language :: Python :: 3
Requires-Python: >=3.8
Requires-Dist: aiomysql>=0.2.0
Requires-Dist: asyncpg>=0.29.0
Requires-Dist: beautifulsoup4>=4.12.2
Requires-Dist: psycopg2-binary>=2.9.9
Requires-Dist: pymysql>=1.1.0
Requires-Dist: redis>=5.0.0
